spd_trading/__init__.py
spd_trading/historical_density.py
spd_trading/kernel.py
spd_trading/risk_neutral_density.py
spd_trading/config/__init__.py
spd_trading/config/core.py
spd_trading/utils/__init__.py
spd_trading/utils/density.py
spd_trading/utils/smoothing.py
spd_trading-0.1.3.dist-info/LICENSE
spd_trading-0.1.3.dist-info/METADATA
spd_trading-0.1.3.dist-info/WHEEL
spd_trading-0.1.3.dist-info/top_level.txt
spd_trading-0.1.3.dist-info/RECORD
