Metadata-Version: 2.1
Name: spd-trading
Version: 0.1.3
Summary: Estimates the Risk Neutral Density and Historical Density of an underlying and suggests trading intervals based on the Pricing Kernel.
Home-page: https://github.com/franwe/spd_trading
Author: franwe
Author-email: franziska.wehrmann@gmail.com
License: MIT
Project-URL: Documentation, https://spd_trading.readthedocs.io/en/latest/
Project-URL: Code, https://github.com/franwe/spd_trading
Platform: UNKNOWN
Requires-Python: >=3.9
Requires-Dist: numpy (==1.21.0)
Requires-Dist: pandas (==1.3.0)
Requires-Dist: scipy (==1.7.0)
Requires-Dist: arch (==4.19)
Requires-Dist: localpoly (==0.1.4)
Requires-Dist: sklearn (==0.0)
Requires-Dist: matplotlib (==3.4.2)
Requires-Dist: statsmodels (==0.12.2)
